{"meta":{"network":"xdai"},"data":{"id":"069fbb33-369e-42e6-a928-a283465c35f2","type":"card-spaces","attributes":{"did":"did:cardstack:1c1PrAyKAif7f93oB4YrqYkU02c7fe80955d6545","profile-name":null,"profile-description":null,"profile-category":null,"profile-cover-image-url":null,"profile-button-text":null,"bio-title":null,"bio-description":null,"links":[],"donation-title":null,"donation-description":null,"donation-suggestion-amount-1":null,"donation-suggestion-amount-2":null,"donation-suggestion-amount-3":null,"donation-suggestion-amount-4":null},"relationships":{"merchant-info":{"data":{"type":"merchant-infos","id":"a737f756-b00b-40ed-b782-f4652b480925"}}}}}