{"meta":{"network":"xdai"},"data":{"id":"2ad41e00-8ed8-441e-96ea-93044db1c271","type":"card-spaces","attributes":{"did":"did:cardstack:1c6hK3fnRnoKehajqUjrR8iB9b203cf077cf870c","profile-name":null,"profile-description":null,"profile-category":null,"profile-cover-image-url":null,"profile-button-text":null,"bio-title":null,"bio-description":null,"links":[],"donation-title":null,"donation-description":null,"donation-suggestion-amount-1":null,"donation-suggestion-amount-2":null,"donation-suggestion-amount-3":null,"donation-suggestion-amount-4":null},"relationships":{"merchant-info":{"data":{"type":"merchant-infos","id":"2db6b083-2952-48ac-ae5d-6be518cd37e3"}}}}}