{"meta":{"network":"xdai"},"data":{"id":"3543230d-1a26-47bf-a48f-4290c9131ac0","type":"card-spaces","attributes":{"did":"did:cardstack:1cs7ztcpCno7Qm7iZQxZVb6Kf47f9b742ca9f982f","profile-name":null,"profile-description":null,"profile-category":null,"profile-cover-image-url":null,"profile-button-text":null,"bio-title":null,"bio-description":null,"links":[],"donation-title":null,"donation-description":null,"donation-suggestion-amount-1":null,"donation-suggestion-amount-2":null,"donation-suggestion-amount-3":null,"donation-suggestion-amount-4":null},"relationships":{"merchant-info":{"data":{"type":"merchant-infos","id":"0888cae6-3a28-4203-b58d-91d9ac68e6db"}}}}}