{"meta":{"network":"xdai"},"data":{"id":"3d30e266-7621-4e4c-a38b-8cd119e8071b","type":"card-spaces","attributes":{"did":"did:cardstack:1cs8yfMF8ec5r6mZVUtYxuYGt652bf85bc06a5a6a","profile-name":null,"profile-description":null,"profile-category":null,"profile-cover-image-url":null,"profile-button-text":null,"bio-title":null,"bio-description":null,"links":[],"donation-title":null,"donation-description":null,"donation-suggestion-amount-1":null,"donation-suggestion-amount-2":null,"donation-suggestion-amount-3":null,"donation-suggestion-amount-4":null},"relationships":{"merchant-info":{"data":{"type":"merchant-infos","id":"2a73e756-2c99-4af7-a9b5-01f6351b16ca"}}}}}