{"meta":{"network":"xdai"},"data":{"id":"4710eb72-f4fa-4ee6-90ed-65641b726269","type":"card-spaces","attributes":{"did":"did:cardstack:1cs9LYVXCH3ZHB1Jr3TWnfXvtee093d1e1189a638","profile-name":null,"profile-description":null,"profile-category":null,"profile-cover-image-url":null,"profile-button-text":null,"bio-title":null,"bio-description":null,"links":[],"donation-title":null,"donation-description":null,"donation-suggestion-amount-1":null,"donation-suggestion-amount-2":null,"donation-suggestion-amount-3":null,"donation-suggestion-amount-4":null},"relationships":{"merchant-info":{"data":{"type":"merchant-infos","id":"bc2bfbfc-550b-4d1f-bc94-755f69568700"}}}}}