{"meta":{"network":"xdai"},"data":{"id":"4ae858e2-de82-46ef-8132-2926a1d0615f","type":"card-spaces","attributes":{"did":"did:cardstack:1cafuGy1r6LB6efAJ7LynRtn310fdccae367710f","profile-name":null,"profile-description":null,"profile-category":null,"profile-cover-image-url":null,"profile-button-text":null,"bio-title":null,"bio-description":null,"links":[],"donation-title":null,"donation-description":null,"donation-suggestion-amount-1":null,"donation-suggestion-amount-2":null,"donation-suggestion-amount-3":null,"donation-suggestion-amount-4":null},"relationships":{"merchant-info":{"data":{"type":"merchant-infos","id":"43d510ea-d19e-45dd-b8d4-841cbd428950"}}}}}