{"meta":{"network":"xdai"},"data":{"id":"4b1b73b7-0d78-4aff-a7ec-f4223ac6c136","type":"card-spaces","attributes":{"did":"did:cardstack:1csagVCfbuRqNedZBXvajk3X1631e336843b5d245","profile-name":null,"profile-description":null,"profile-category":null,"profile-cover-image-url":null,"profile-button-text":null,"bio-title":null,"bio-description":null,"links":[],"donation-title":null,"donation-description":null,"donation-suggestion-amount-1":null,"donation-suggestion-amount-2":null,"donation-suggestion-amount-3":null,"donation-suggestion-amount-4":null},"relationships":{"merchant-info":{"data":{"type":"merchant-infos","id":"38074834-741f-408c-8df7-a9af98965936"}}}}}