{"meta":{"network":"xdai"},"data":{"id":"5f882e91-4f1d-429a-9d0e-24a4d3146e34","type":"card-spaces","attributes":{"did":"did:cardstack:1cscNd5vNQ3nsE2ea3B287No194503325505f96db","profile-name":null,"profile-description":null,"profile-category":null,"profile-cover-image-url":null,"profile-button-text":null,"bio-title":null,"bio-description":null,"links":[],"donation-title":null,"donation-description":null,"donation-suggestion-amount-1":null,"donation-suggestion-amount-2":null,"donation-suggestion-amount-3":null,"donation-suggestion-amount-4":null},"relationships":{"merchant-info":{"data":{"type":"merchant-infos","id":"17854b06-d186-4e7e-acad-6190a58ab803"}}}}}