{"meta":{"network":"xdai"},"data":{"id":"ae35b801-9f13-4273-9e9b-ba6edea15799","type":"card-spaces","attributes":{"did":"did:cardstack:1cnvGXdCpzXkeiubrCnjxwU2bf46d5ffb626f87f","profile-name":null,"profile-description":null,"profile-category":null,"profile-cover-image-url":null,"profile-button-text":null,"bio-title":null,"bio-description":null,"links":[],"donation-title":null,"donation-description":null,"donation-suggestion-amount-1":null,"donation-suggestion-amount-2":null,"donation-suggestion-amount-3":null,"donation-suggestion-amount-4":null},"relationships":{"merchant-info":{"data":{"type":"merchant-infos","id":"7099aa7f-ec38-4d78-8714-519f50258602"}}}}}