{"meta":{"network":"xdai"},"data":{"id":"b4ca38c7-9dd1-4654-a351-7f9cfaa10f2f","type":"card-spaces","attributes":{"did":"did:cardstack:1csojQk3CU8guEvPcS1yqQpKV876eeb12d26ec7be","profile-name":null,"profile-description":null,"profile-category":null,"profile-cover-image-url":null,"profile-button-text":null,"bio-title":null,"bio-description":null,"links":[],"donation-title":null,"donation-description":null,"donation-suggestion-amount-1":null,"donation-suggestion-amount-2":null,"donation-suggestion-amount-3":null,"donation-suggestion-amount-4":null},"relationships":{"merchant-info":{"data":{"type":"merchant-infos","id":"fa66f3b3-42d4-40d0-8a2e-56d40ea2fbd0"}}}}}