{"meta":{"network":"xdai"},"data":{"id":"c3eec287-d63c-4d93-bbb2-98fe5b30df93","type":"card-spaces","attributes":{"did":"did:cardstack:1cqchCJ6twVvgynnHXSGuain30ff4156525c1019","profile-name":null,"profile-description":null,"profile-category":null,"profile-cover-image-url":null,"profile-button-text":null,"bio-title":null,"bio-description":null,"links":[],"donation-title":null,"donation-description":null,"donation-suggestion-amount-1":null,"donation-suggestion-amount-2":null,"donation-suggestion-amount-3":null,"donation-suggestion-amount-4":null},"relationships":{"merchant-info":{"data":{"type":"merchant-infos","id":"41b17dfe-342b-40e1-be89-e389986b7aa0"}}}}}