{"meta":{"network":"xdai"},"data":{"id":"d04bb232-2e69-41bf-8b5a-abc1f2f2cbbb","type":"card-spaces","attributes":{"did":"did:cardstack:1csrHQfup1rtUpztjvAZ7sUCTf9bbbf3e3911a519","profile-name":null,"profile-description":null,"profile-category":null,"profile-cover-image-url":null,"profile-button-text":null,"bio-title":null,"bio-description":null,"links":[],"donation-title":null,"donation-description":null,"donation-suggestion-amount-1":null,"donation-suggestion-amount-2":null,"donation-suggestion-amount-3":null,"donation-suggestion-amount-4":null},"relationships":{"merchant-info":{"data":{"type":"merchant-infos","id":"06ffd101-180a-4ccb-97c2-74ffe641c307"}}}}}